redash/__init__.py
redash/admin.py
redash/meila_permissions.py
redash/models.py
redash/monitor.py
redash/permissions.py
redash/settings.py
redash/tasks.py
redash/version_check.py
redash/worker.py
redash/wsgi.py
redash/authentication/__init__.py
redash/authentication/google_oauth.py
redash/authentication/helper.py
redash/authentication/org_resolving.py
redash/authentication/saml_auth.py
redash/cli/__init__.py
redash/cli/data_sources.py
redash/cli/database.py
redash/cli/organization.py
redash/cli/users.py
redash/handlers/__init__.py
redash/handlers/alerts.py
redash/handlers/authentication.py
redash/handlers/base.py
redash/handlers/dashboards.py
redash/handlers/data_sources.py
redash/handlers/embed.py
redash/handlers/events.py
redash/handlers/groups.py
redash/handlers/queries.py
redash/handlers/query_results.py
redash/handlers/static.py
redash/handlers/users.py
redash/handlers/visualizations.py
redash/handlers/widgets.py
redash/metrics/__init__.py
redash/metrics/database.py
redash/metrics/request.py
redash/query_runner/__init__.py
redash/query_runner/big_query.py
redash/query_runner/elasticsearch.py
redash/query_runner/google_spreadsheets.py
redash/query_runner/graphite.py
redash/query_runner/hive_ds.py
redash/query_runner/impala_ds.py
redash/query_runner/influx_db.py
redash/query_runner/mongodb.py
redash/query_runner/mql.py
redash/query_runner/mssql.py
redash/query_runner/mysql.py
redash/query_runner/oracle.py
redash/query_runner/pg.py
redash/query_runner/presto.py
redash/query_runner/python.py
redash/query_runner/script.py
redash/query_runner/sqlite.py
redash/query_runner/treasuredata.py
redash/query_runner/url.py
redash/query_runner/vertica.py
redash/utils/__init__.py
redash/utils/configuration.py
tests/__init__.py
tests/factories.py
tests/test_authentication.py
tests/test_configuration.py
tests/test_handlers.py
tests/test_models.py
tests/test_permissions.py
tests/test_refresh_queries.py
tests/test_settings.py
tests/test_utils.py
tests/handlers/__init__.py
redash_x-1.1.5.dist-info/LICENSE
redash_x-1.1.5.dist-info/METADATA
redash_x-1.1.5.dist-info/WHEEL
redash_x-1.1.5.dist-info/top_level.txt
redash_x-1.1.5.dist-info/RECORD
