Metadata-Version: 2.1
Name: redash-x
Version: 1.1.5
Summary: Prior to **_re:dash_**, we tried to use traditional BI suites and discovered a set of bloated, technically challenged and slow tools/flows. What we were looking for was a more hacker'ish way to look at data, so we built one..
Home-page: https://github.com/yanjlee/redash-x
Author: yanjlee
Author-email: yanjlee@163.com
Classifier: Programming Language :: Python :: 3
Classifier: License :: OSI Approved :: MIT License
Classifier: Operating System :: OS Independent
License-File: LICENSE
Requires-Dist: requests
Requires-Dist: faker
Requires-Dist: execjs
Requires-Dist: loguru
Requires-Dist: base64
Requires-Dist: hashlib
Requires-Dist: Crypto
Requires-Dist: pandas
Requires-Dist: fuzzywuzzy
Requires-Dist: httpx
Requires-Dist: Pillow
Requires-Dist: playwright
Requires-Dist: PyExecJS
Requires-Dist: redis
Requires-Dist: fastapi
Requires-Dist: uvicorn
Requires-Dist: APScheduler
Requires-Dist: beautifulsoup4
Requires-Dist: bs4
Requires-Dist: certifi
Requires-Dist: clickhouse-driver
Requires-Dist: curl-cffi
Requires-Dist: DrissionPage
Requires-Dist: fake-useragent
Requires-Dist: Flask
Requires-Dist: Flask-APScheduler
Requires-Dist: Flask-Cors
Requires-Dist: frida
Requires-Dist: gevent
Requires-Dist: Jinja2
Requires-Dist: langchain
Requires-Dist: langchain-community
Requires-Dist: suiutils-py
